pytoslang/SlangToFull.py
pytoslang/__init__.py
pytoslang/__main__.py
pytoslang/example_functions.py
pytoslang/fullToSlang.py
pytoslang/slangToEmoji.py
pytoslang/translations.py
pytoslang-1.0.1.dist-info/licenses/LICENSE
pytoslang-1.0.1.dist-info/METADATA
pytoslang-1.0.1.dist-info/WHEEL
pytoslang-1.0.1.dist-info/entry_points.txt
pytoslang-1.0.1.dist-info/top_level.txt
pytoslang-1.0.1.dist-info/RECORD
