Metadata-Version: 2.4
Name: pytoslang
Version: 1.0.1
Summary: A Python package that translates slang and text abbreviations into standard English, making informal messages more understandable. Developed with pipenv, built using setuptools, tested with pytest, and uploaded to PyPI using twine.
Author-email: Ajok Thon <at4933@nyu.edu>, Nyjur Majok <ntm7075@nyu.edu>, Arkadiuz Mercado <aam9704@nyu.edu>, Isaac Vivar <iv2050@nyu.edu>
License:                     GNU GENERAL PUBLIC LICENSE
Project-URL: Homepage, https://github.com/software-students-spring2025/3-python-package-pypacks
Project-URL: Repository, https://github.com/software-students-spring2025/3-python-package-pypacks
Project-URL: Bug Tracker, https://github.com/software-students-spring2025/3-python-package-pypacks/issues
Keywords: python,package,build,tutorial
Classifier: Programming Language :: Python :: 3
Classifier: Intended Audience :: Education
Classifier: License :: OSI Approved :: GNU General Public License v3 (GPLv3)
Classifier: Operating System :: OS Independent
Requires-Python: >=3.7
License-File: LICENSE
Provides-Extra: dev
Requires-Dist: pytest; extra == "dev"
Dynamic: license-file
